Dockerfile
LICENSE
README.md
aleph_message/__init__.py
aleph_message/exceptions.py
aleph_message/py.typed
aleph_message/status.py
aleph_message/utils.py
aleph_message/models/__init__.py
aleph_message/models/abstract.py
aleph_message/models/base.py
aleph_message/models/item_hash.py
aleph_message/models/execution/__init__.py
aleph_message/models/execution/abstract.py
aleph_message/models/execution/base.py
aleph_message/models/execution/environment.py
aleph_message/models/execution/instance.py
aleph_message/models/execution/program.py
aleph_message/models/execution/volume.py
aleph_message/tests/__init__.py
aleph_message/tests/download_messages.py
aleph_message/tests/test_models.py
aleph_message/tests/test_status.py
aleph_message/tests/test_types.py
aleph_message/tests/test_utils.py
aleph_message/tests/messages/forget.json
aleph_message/tests/messages/instance_confidential_machine.json
aleph_message/tests/messages/instance_content.json
aleph_message/tests/messages/instance_gpu_machine.json
aleph_message/tests/messages/instance_machine.json
aleph_message/tests/messages/machine.json
aleph_message/tests/messages/machine_named.json
pyproject.toml
aleph_message-1.0.5.dist-info/METADATA
aleph_message-1.0.5.dist-info/WHEEL
aleph_message-1.0.5.dist-info/licenses/LICENSE
aleph_message-1.0.5.dist-info/RECORD
