Metadata-Version: 2.4
Name: aleph-message
Version: 1.0.5
Summary: Aleph.im message specification
Project-URL: Documentation, https://aleph.im/
Project-URL: Homepage, https://github.com/aleph-im/aleph-message
Author-email: Hugo Herter <git@hugoherter.com>
License: MIT License
License-File: LICENSE
Classifier: Development Status :: 5 - Production/Stable
Classifier: Intended Audience :: Developers
Classifier: Programming Language :: Python :: 3 :: Only
Classifier: Programming Language :: Python :: 3.8
Classifier: Programming Language :: Python :: 3.9
Classifier: Programming Language :: Python :: 3.10
Classifier: Programming Language :: Python :: 3.11
Classifier: Programming Language :: Python :: 3.12
Classifier: Topic :: System :: Distributed Computing
Requires-Python: >=3
Requires-Dist: pydantic-core>=2
Requires-Dist: pydantic>=2
Requires-Dist: typing-extensions>=4.5
